scipy/__config__.py
scipy/conftest.py
scipy/__init__.py
scipy/version.py
scipy/_distributor_init.py
scipy/fftpack/convolve.cpython-312-x86_64-linux-gnu.so
scipy/fftpack/_basic.py
scipy/fftpack/helper.py
scipy/fftpack/basic.py
scipy/fftpack/__init__.py
scipy/fftpack/realtransforms.py
scipy/fftpack/_pseudo_diffs.py
scipy/fftpack/_helper.py
scipy/fftpack/_realtransforms.py
scipy/fftpack/pseudo_diffs.py
scipy/fftpack/tests/fftw_longdouble_ref.npz
scipy/fftpack/tests/test_pseudo_diffs.py
scipy/fftpack/tests/test_basic.py
scipy/fftpack/tests/test.npz
scipy/fftpack/tests/__init__.py
scipy/fftpack/tests/fftw_single_ref.npz
scipy/fftpack/tests/test_helper.py
scipy/fftpack/tests/fftw_double_ref.npz
scipy/fftpack/tests/test_real_transforms.py
scipy/fftpack/tests/test_import.py
scipy/io/_test_fortran.cpython-312-x86_64-linux-gnu.so
scipy/io/harwell_boeing.py
scipy/io/wavfile.py
scipy/io/_fortran.py
scipy/io/_netcdf.py
scipy/io/idl.py
scipy/io/__init__.py
scipy/io/netcdf.py
scipy/io/mmio.py
scipy/io/_mmio.py
scipy/io/_idl.py
scipy/io/tests/test_fortran.py
scipy/io/tests/test_paths.py
scipy/io/tests/__init__.py
scipy/io/tests/test_wavfile.py
scipy/io/tests/test_mmio.py
scipy/io/tests/test_idl.py
scipy/io/tests/test_netcdf.py
scipy/io/tests/data/scalar_string.sav
scipy/io/tests/data/struct_pointer_arrays_replicated_3d.sav
scipy/io/tests/data/array_float32_pointer_1d.sav
scipy/io/tests/data/struct_arrays.sav
scipy/io/tests/data/array_float32_5d.sav
scipy/io/tests/data/struct_scalars_replicated_3d.sav
scipy/io/tests/data/null_pointer.sav
scipy/io/tests/data/fortran-mixed.dat
scipy/io/tests/data/array_float32_pointer_2d.sav
scipy/io/tests/data/struct_arrays_byte_idl80.sav
scipy/io/tests/data/example_2.nc
scipy/io/tests/data/scalar_uint64.sav
scipy/io/tests/data/test-8000Hz-le-3ch-5S-64bit.wav
scipy/io/tests/data/struct_pointer_arrays_replicated.sav
scipy/io/tests/data/scalar_uint16.sav
scipy-1.15.0.dist-info/RECORD
scipy-1.15.0.dist-info/LICENSE.txt
scipy-1.15.0.dist-info/METADATA
scipy-1.15.0.dist-info/WHEEL
