Metadata-Version: 2.1
Name: scipy
Version: 1.15.0
Summary: Fundamental algorithms for scientific computing in Python
Maintainer-Email: SciPy Developers <scipy-dev@python.org>
License: Copyright (c) 2001-2002 Enthought, Inc. 2003-2024, SciPy Developers.
Classifier: Development Status :: 5 - Production/Stable
Classifier: Intended Audience :: Science/Research
Classifier: Intended Audience :: Developers
Classifier: License :: OSI Approved :: BSD License
Classifier: Programming Language :: C
Classifier: Programming Language :: Python
Classifier: Programming Language :: Python :: 3
Classifier: Programming Language :: Python :: 3.10
Classifier: Programming Language :: Python :: 3.11
Classifier: Programming Language :: Python :: 3.12
Classifier: Programming Language :: Python :: 3.13
Classifier: Topic :: Software Development :: Libraries
Classifier: Topic :: Scientific/Engineering
Classifier: Operating System :: Microsoft :: Windows
Classifier: Operating System :: POSIX :: Linux
Classifier: Operating System :: POSIX
Classifier: Operating System :: Unix
Classifier: Operating System :: MacOS
Project-URL: homepage, https://scipy.org/
Project-URL: documentation, https://docs.scipy.org/doc/scipy/
Project-URL: source, https://github.com/scipy/scipy
Project-URL: download, https://github.com/scipy/scipy/releases
Project-URL: tracker, https://github.com/scipy/scipy/issues
Requires-Python: >=3.10
Requires-Dist: numpy<2.5,>=1.23.5
Provides-Extra: test
Requires-Dist: pytest; extra == "test"
Requires-Dist: pytest-cov; extra == "test"
Requires-Dist: pytest-timeout; extra == "test"
Requires-Dist: pytest-xdist; extra == "test"
Requires-Dist: asv; extra == "test"
Requires-Dist: mpmath; extra == "test"
Requires-Dist: gmpy2; extra == "test"
Requires-Dist: threadpoolctl; extra == "test"
Requires-Dist: scikit-umfpack; extra == "test"
Requires-Dist: pooch; extra == "test"
Requires-Dist: hypothesis>=6.30; extra == "test"
Requires-Dist: array-api-strict<2.1.1,>=2.0; extra == "test"
Requires-Dist: Cython; extra == "test"
Requires-Dist: meson; extra == "test"
Requires-Dist: ninja; sys_platform != "emscripten" and extra == "test"
Provides-Extra: doc
Requires-Dist: sphinx<8.0.0,>=5.0.0; extra == "doc"
Requires-Dist: intersphinx_registry; extra == "doc"
Requires-Dist: pydata-sphinx-theme>=0.15.2; extra == "doc"
Requires-Dist: sphinx-copybutton; extra == "doc"
Requires-Dist: sphinx-design>=0.4.0; extra == "doc"
Requires-Dist: matplotlib>=3.5; extra == "doc"
Requires-Dist: numpydoc; extra == "doc"
Requires-Dist: jupytext; extra == "doc"
Requires-Dist: myst-nb; extra == "doc"
Requires-Dist: pooch; extra == "doc"
Requires-Dist: jupyterlite-sphinx>=0.16.5; extra == "doc"
Requires-Dist: jupyterlite-pyodide-kernel; extra == "doc"
Provides-Extra: dev
Requires-Dist: mypy==1.10.0; extra == "dev"
Requires-Dist: typing_extensions; extra == "dev"
Requires-Dist: types-psutil; extra == "dev"
Requires-Dist: pycodestyle; extra == "dev"
Requires-Dist: ruff>=0.0.292; extra == "dev"
Requires-Dist: cython-lint>=0.12.2; extra == "dev"
Requires-Dist: rich-click; extra == "dev"
Requires-Dist: doit>=0.36.0; extra == "dev"
Requires-Dist: pydevtool; extra == "dev"
